{
  "version_juego": "1.49.5",
  "descripcion": "Grafo de crafteo. Nodos = items; aristas = ingredientes. Acíclico. estacion:null = a mano o solo loot. produce = unidades por crafteo (default 1). verificado: wiki|ingame (ante conflicto gana ingame).",
  "items": [
    { "id": "tronco-pino", "nombre": "Tronco de pino", "estacion": null, "ingredientes": [], "verificado": "wiki" },
    { "id": "tronco-roble", "nombre": "Tronco de roble", "estacion": null, "ingredientes": [], "verificado": "wiki" },
    { "id": "caliza", "nombre": "Caliza", "estacion": null, "ingredientes": [], "verificado": "wiki" },
    { "id": "mineral-hierro", "nombre": "Mineral de hierro", "estacion": null, "ingredientes": [], "verificado": "wiki" },
    { "id": "chatarra", "nombre": "Chatarra", "estacion": null, "ingredientes": [], "verificado": "wiki" },
    { "id": "bauxita", "nombre": "Bauxita", "estacion": null, "ingredientes": [], "verificado": "wiki" },
    { "id": "cable-aluminio", "nombre": "Cable de aluminio", "estacion": null, "ingredientes": [], "verificado": "wiki" },
    { "id": "mineral-cobre", "nombre": "Mineral de cobre", "estacion": null, "ingredientes": [], "verificado": "wiki" },
    { "id": "mineral-titanio", "nombre": "Mineral de titanio", "estacion": null, "ingredientes": [], "verificado": "wiki" },
    { "id": "fibra", "nombre": "Fibra", "estacion": null, "ingredientes": [], "verificado": "wiki" },
    { "id": "trozo-lana", "nombre": "Trozo de lana", "estacion": null, "ingredientes": [], "verificado": "wiki" },
    { "id": "cuero-crudo", "nombre": "Cuero crudo", "estacion": null, "ingredientes": [], "verificado": "wiki" },
    { "id": "piel", "nombre": "Piel", "estacion": null, "ingredientes": [], "verificado": "wiki" },
    { "id": "adhesivo", "nombre": "Adhesivo", "estacion": null, "ingredientes": [], "verificado": "wiki" },
    { "id": "plastico", "nombre": "Plástico", "estacion": null, "ingredientes": [], "verificado": "wiki" },
    { "id": "piezas-motor", "nombre": "Piezas de motor", "estacion": null, "ingredientes": [], "verificado": "wiki" },
    { "id": "cableado", "nombre": "Cableado", "estacion": null, "ingredientes": [], "verificado": "wiki" },
    { "id": "rodamientos", "nombre": "Rodamientos", "estacion": null, "ingredientes": [], "verificado": "wiki" },
    { "id": "piezas-goma", "nombre": "Piezas de goma", "estacion": null, "ingredientes": [], "verificado": "wiki" },
    { "id": "ruedas-chopper", "nombre": "Ruedas de chopper", "estacion": null, "ingredientes": [], "verificado": "wiki" },
    { "id": "horquilla-chopper", "nombre": "Horquilla de chopper", "estacion": null, "ingredientes": [], "verificado": "wiki" },
    { "id": "deposito-chopper", "nombre": "Depósito de chopper", "estacion": null, "ingredientes": [], "verificado": "wiki" },
    { "id": "mochila-basica", "nombre": "Mochila básica", "estacion": null, "ingredientes": [], "verificado": "wiki" },
    { "id": "carta-cac-a", "nombre": "Carta de acceso CAC A", "estacion": null, "ingredientes": [], "verificado": "wiki" },
    { "id": "ruedas-atv", "nombre": "Ruedas de ATV", "estacion": null, "ingredientes": [], "verificado": "wiki" },
    { "id": "transmision-atv", "nombre": "Transmisión de ATV", "estacion": null, "ingredientes": [], "verificado": "wiki" },
    { "id": "deposito-atv", "nombre": "Depósito de ATV", "estacion": null, "ingredientes": [], "verificado": "wiki" },
    { "id": "helice", "nombre": "Hélice", "estacion": null, "ingredientes": [], "verificado": "wiki" },
    { "id": "llave-inglesa", "nombre": "Llave inglesa", "estacion": null, "ingredientes": [], "verificado": "wiki" },
    { "id": "filtro-aire", "nombre": "Filtro de aire", "estacion": null, "ingredientes": [], "verificado": "wiki" },
    { "id": "gorro-piel", "nombre": "Gorro de piel", "estacion": "Mesa de costura", "ingredientes": [], "verificado": "wiki", "notas": "Receta por verificar in-game (F3.2); tratado como hoja hasta entonces" },
    { "id": "chaqueta-piel", "nombre": "Chaqueta de piel", "estacion": "Mesa de costura", "ingredientes": [], "verificado": "wiki", "notas": "Receta por verificar in-game (F3.2); tratado como hoja hasta entonces" },

    { "id": "tablon-pino", "nombre": "Tablón de pino", "estacion": "Carpintería", "ingredientes": [{ "id": "tronco-pino", "qty": 1 }], "verificado": "wiki" },
    { "id": "tablon-roble", "nombre": "Tablón de roble", "estacion": "Carpintería", "ingredientes": [{ "id": "tronco-roble", "qty": 1 }], "verificado": "wiki" },
    { "id": "carbon", "nombre": "Carbón", "estacion": "Fundición", "ingredientes": [{ "id": "tronco-pino", "qty": 1 }], "verificado": "wiki" },
    { "id": "ladrillo-piedra", "nombre": "Ladrillo de piedra", "estacion": "Mesa del cantero", "ingredientes": [{ "id": "caliza", "qty": 1 }], "verificado": "wiki" },
    { "id": "lingote-hierro", "nombre": "Lingote de hierro", "estacion": "Fundición", "ingredientes": [{ "id": "mineral-hierro", "qty": 1 }], "alternativas": [[{ "id": "chatarra", "qty": 1 }]], "verificado": "wiki" },
    { "id": "placa-hierro", "nombre": "Placa de hierro", "estacion": "Banco de trabajo", "tiempo": "20m", "ingredientes": [{ "id": "lingote-hierro", "qty": 1 }], "verificado": "wiki" },
    { "id": "clavos", "nombre": "Clavos", "estacion": "Banco de trabajo", "produce": 2, "ingredientes": [{ "id": "placa-hierro", "qty": 1 }], "verificado": "wiki" },
    { "id": "lingote-aluminio", "nombre": "Lingote de aluminio", "estacion": "Fundición", "ingredientes": [{ "id": "bauxita", "qty": 5 }], "alternativas": [[{ "id": "cable-aluminio", "qty": 2 }]], "verificado": "wiki" },
    { "id": "placa-aluminio", "nombre": "Placa de aluminio", "estacion": "Banco de trabajo", "tiempo": "1h", "ingredientes": [{ "id": "lingote-aluminio", "qty": 2 }], "verificado": "wiki" },
    { "id": "pernos", "nombre": "Pernos", "estacion": "Banco de trabajo", "produce": 2, "ingredientes": [{ "id": "placa-aluminio", "qty": 1 }], "verificado": "wiki" },
    { "id": "lingote-cobre", "nombre": "Lingote de cobre", "estacion": "Fundición", "ingredientes": [{ "id": "mineral-cobre", "qty": 1 }], "verificado": "wiki" },
    { "id": "lingote-acero", "nombre": "Lingote de acero", "estacion": "Fundición refinada", "tiempo": "1h30", "ingredientes": [{ "id": "lingote-hierro", "qty": 1 }, { "id": "lingote-aluminio", "qty": 1 }, { "id": "lingote-cobre", "qty": 1 }, { "id": "carbon", "qty": 2 }], "verificado": "wiki" },
    { "id": "placa-acero", "nombre": "Placa de acero", "estacion": "Banco de trabajo", "tiempo": "1h", "ingredientes": [{ "id": "lingote-acero", "qty": 1 }], "verificado": "wiki" },
    { "id": "lingote-titanio", "nombre": "Lingote de titanio", "estacion": "Extractor (isla)", "ingredientes": [{ "id": "mineral-titanio", "qty": 1 }], "verificado": "wiki" },
    { "id": "trozo-tela", "nombre": "Trozo de tela", "estacion": null, "ingredientes": [{ "id": "fibra", "qty": 1 }], "verificado": "wiki", "notas": "Cantidad por verificar in-game" },
    { "id": "tela-gruesa", "nombre": "Tela gruesa", "estacion": "Mesa de costura", "ingredientes": [{ "id": "trozo-tela", "qty": 1 }], "verificado": "wiki", "notas": "Cantidad por verificar in-game" },
    { "id": "tela-lana", "nombre": "Tela de lana", "estacion": "Mesa de costura", "tiempo": "12m", "ingredientes": [{ "id": "trozo-lana", "qty": 2 }], "verificado": "wiki" },
    { "id": "cuero", "nombre": "Cuero", "estacion": "Curtidor", "tiempo": "4m", "ingredientes": [{ "id": "cuero-crudo", "qty": 1 }], "verificado": "wiki" },
    { "id": "piel-curtida", "nombre": "Piel curtida", "estacion": "Curtidor", "ingredientes": [{ "id": "piel", "qty": 1 }], "verificado": "wiki" },

    { "id": "pantalones-piel", "nombre": "Pantalones de piel", "estacion": "Mesa de costura", "ingredientes": [{ "id": "piel-curtida", "qty": 6 }, { "id": "cuero", "qty": 3 }, { "id": "tela-gruesa", "qty": 6 }, { "id": "placa-hierro", "qty": 2 }, { "id": "adhesivo", "qty": 2 }], "verificado": "wiki" },
    { "id": "botas-piel", "nombre": "Botas de piel", "estacion": "Mesa de costura", "ingredientes": [{ "id": "piel-curtida", "qty": 4 }, { "id": "cuero", "qty": 2 }, { "id": "tela-gruesa", "qty": 3 }, { "id": "placa-hierro", "qty": 1 }, { "id": "adhesivo", "qty": 1 }], "verificado": "wiki" },
    { "id": "pantalones-piel-reforzados", "nombre": "Pantalones de piel reforzados", "estacion": "Mesa de costura", "ingredientes": [{ "id": "pantalones-piel", "qty": 1 }, { "id": "piel-curtida", "qty": 12 }, { "id": "tela-lana", "qty": 9 }, { "id": "cuero", "qty": 2 }, { "id": "placa-hierro", "qty": 2 }, { "id": "placa-acero", "qty": 5 }], "verificado": "ingame", "notas": "Captura de Alin (misión Protección contra el frío)" },
    { "id": "gorro-piel-reforzado", "nombre": "Gorro de piel reforzado", "estacion": "Mesa de costura", "ingredientes": [{ "id": "gorro-piel", "qty": 1 }, { "id": "piel-curtida", "qty": 9 }, { "id": "tela-lana", "qty": 5 }, { "id": "cuero", "qty": 1 }, { "id": "lingote-cobre", "qty": 1 }, { "id": "placa-hierro", "qty": 3 }], "verificado": "wiki" },
    { "id": "chaqueta-piel-reforzada", "nombre": "Chaqueta de piel reforzada", "estacion": "Mesa de costura", "ingredientes": [{ "id": "chaqueta-piel", "qty": 1 }, { "id": "piel-curtida", "qty": 12 }, { "id": "tela-lana", "qty": 9 }, { "id": "cuero", "qty": 2 }, { "id": "lingote-cobre", "qty": 2 }, { "id": "placa-hierro", "qty": 5 }], "verificado": "wiki" }
  ]
}
